Workbook

Sheet Vendas
A1: Lumos 3D — Controle de Vendas
A2: Preencha uma linha por venda. Datas em azul e campos de texto/valor em azul são para você editar.
A4: Data | B4: Produto | C4: Valor | D4: Forma de pagamento | E4: Cliente
A5: 46237 | B5: Chaveiro personalizado (unidade) | C5: 25 | D5: Pix | E5: Maria Souza
A6: 46239 | B6: Kit brinde corporativo (50 un) | C6: 950 | D6: Cartão de crédito | E6: Empresa ABC Ltda
A7: 46242 | B7: Luminária com nome | C7: 89.9 | D7: Pix | E7: João Pereira
A8: 46246 | B8: Porta retrato personalizado | C8: 45 | D8: Boleto | E8: Ana Lima
A9: 46249 | B9: Troféu personalizado (10 un) | C9: 320 | D9: Pix | E9: Empresa XYZ Eventos

Sheet Despesas
A1: Lumos 3D — Controle de Despesas
A2: Preencha uma linha por despesa. Datas e valores em azul são para você editar.
A4: Data | B4: Categoria | C4: Valor | D4: Fornecedor
A5: 46235 | B5: Matéria-prima (filamento) | C5: 480 | D5: Fornecedor Filamentos BR
A6: 46238 | B6: Energia elétrica | C6: 210 | D6: Companhia de Energia
A7: 46240 | B7: Embalagem | C7: 95 | D7: Papelaria Kraft
A8: 46244 | B8: Marketing (impulsionamento) | C8: 150 | D8: Meta Ads
A9: 46249 | B9: Manutenção de equipamento | C9: 120 | D9: Assistência Técnica 3D

Sheet Fluxo de caixa
A1: Lumos 3D — Fluxo de Caixa
A2: Entradas e saídas são calculadas automaticamente a partir das abas Vendas e Despesas, por data. Adicione novas linhas de data conforme o mês avança.
A4: Data | B4: Entradas | C4: Saídas | D4: Saldo
A5: 46235 | B5: =SUMIFS(Vendas!$C$5:$C$9,Vendas!$A$5:$A$9,A5) -> 0 | C5: =SUMIFS(Despesas!$C$5:$C$9,Despesas!$A$5:$A$9,A5) -> 480 | D5: =B5-C5 -> -480
A6: 46237 | B6: =SUMIFS(Vendas!$C$5:$C$9,Vendas!$A$5:$A$9,A6) -> 25 | C6: =SUMIFS(Despesas!$C$5:$C$9,Despesas!$A$5:$A$9,A6) -> 0 | D6: =D5+B6-C6 -> -455
A7: 46238 | B7: =SUMIFS(Vendas!$C$5:$C$9,Vendas!$A$5:$A$9,A7) -> 0 | C7: =SUMIFS(Despesas!$C$5:$C$9,Despesas!$A$5:$A$9,A7) -> 210 | D7: =D6+B7-C7 -> -665
A8: 46239 | B8: =SUMIFS(Vendas!$C$5:$C$9,Vendas!$A$5:$A$9,A8) -> 950 | C8: =SUMIFS(Despesas!$C$5:$C$9,Despesas!$A$5:$A$9,A8) -> 0 | D8: =D7+B8-C8 -> 285
A9: 46240 | B9: =SUMIFS(Vendas!$C$5:$C$9,Vendas!$A$5:$A$9,A9) -> 0 | C9: =SUMIFS(Despesas!$C$5:$C$9,Despesas!$A$5:$A$9,A9) -> 95 | D9: =D8+B9-C9 -> 190
A10: 46242 | B10: =SUMIFS(Vendas!$C$5:$C$9,Vendas!$A$5:$A$9,A10) -> 89.9 | C10: =SUMIFS(Despesas!$C$5:$C$9,Despesas!$A$5:$A$9,A10) -> 0 | D10: =D9+B10-C10 -> 279.9
A11: 46244 | B11: =SUMIFS(Vendas!$C$5:$C$9,Vendas!$A$5:$A$9,A11) -> 0 | C11: =SUMIFS(Despesas!$C$5:$C$9,Despesas!$A$5:$A$9,A11) -> 150 | D11: =D10+B11-C11 -> 129.9
A12: 46246 | B12: =SUMIFS(Vendas!$C$5:$C$9,Vendas!$A$5:$A$9,A12) -> 45 | C12: =SUMIFS(Despesas!$C$5:$C$9,Despesas!$A$5:$A$9,A12) -> 0 | D12: =D11+B12-C12 -> 174.9
A13: 46249 | B13: =SUMIFS(Vendas!$C$5:$C$9,Vendas!$A$5:$A$9,A13) -> 320 | C13: =SUMIFS(Despesas!$C$5:$C$9,Despesas!$A$5:$A$9,A13) -> 120 | D13: =D12+B13-C13 -> 374.9

Sheet Indicadores
A1: Lumos 3D — Indicadores
A2: Calculado automaticamente a partir das abas Vendas e Despesas. Duplique a linha do mês para acompanhar os meses seguintes, ajustando as datas em azul.
A4: Mês | B4: Faturamento | C4: Despesas | D4: Ticket médio | E4: Margem
A5: Agosto/2026 | B5: =SUMIFS(Vendas!$C$5:$C$9,Vendas!$A$5:$A$9,">="&DATE(2026,8,1),Vendas!$A$5:$A$9,"<"&DATE(2026,9,1)) -> 1429.9 | C5: =SUMIFS(Despesas!$C$5:$C$9,Despesas!$A$5:$A$9,">="&DATE(2026,8,1),Despesas!$A$5:$A$9,"<"&DATE(2026,9,1)) -> 1055 | D5: =IFERROR(B5/COUNTIFS(Vendas!$A$5:$A$9,">="&DATE(2026,8,1),Vendas!$A$5:$A$9,"<"&DATE(2026,9,1)),0) -> 285.98 | E5: =IFERROR((B5-C5)/B5,0) -> 0.26218617
A7: Número de vendas no mês | B7: =COUNTIFS(Vendas!$A$5:$A$9,">="&DATE(2026,8,1),Vendas!$A$5:$A$9,"<"&DATE(2026,9,1)) -> 5
